LICENSE
MANIFEST.in
README.rst
flask_googlefed.py
setup.py
Flask_GoogleFed.egg-info/PKG-INFO
Flask_GoogleFed.egg-info/SOURCES.txt
Flask_GoogleFed.egg-info/dependency_links.txt
Flask_GoogleFed.egg-info/not-zip-safe
Flask_GoogleFed.egg-info/requires.txt
Flask_GoogleFed.egg-info/top_level.txt