Metadata-Version: 1.0
Name: Flask-GoogleFed
Version: 0.1
Summary: Google Federated Logins for Flask.
Home-page: https://github.com/kennethreitz/flask-googlefed
Author: Kennneth Reitz
Author-email: me@kennethreitz.com
License: BSD
Platform: any
Classifier: Environment :: Web Environment
Classifier: Intended Audience :: Developers
Classifier: License :: OSI Approved :: BSD License
Classifier: Operating System :: OS Independent
Classifier: Programming Language :: Python
Classifier: Topic :: Internet :: WWW/HTTP :: Dynamic Content
Classifier: Topic :: Software Development :: Libraries :: Python Modules
